README.md
setup.py
Topsis_Sudeep_101903496/topsis.py
Topsis_Sudeep_101903496.egg-info/PKG-INFO
Topsis_Sudeep_101903496.egg-info/SOURCES.txt
Topsis_Sudeep_101903496.egg-info/dependency_links.txt
Topsis_Sudeep_101903496.egg-info/entry_points.txt
Topsis_Sudeep_101903496.egg-info/requires.txt
Topsis_Sudeep_101903496.egg-info/top_level.txt