Metadata-Version: 2.1
Name: Topsis-Sudeep-101903496
Version: 0.0.3
Summary: A package for calculating Topsis Score and Rank them accordingly
Home-page: https://github.com/sudeepk07/Topsis-Sudeep-101903496
Author: Sudeep Singh
Author-email: singhsudeep0202@gmail.com
License: MIT
Platform: UNKNOWN
Classifier: Programming Language :: Python :: 3
Classifier: License :: OSI Approved :: MIT License
Classifier: Operating System :: OS Independent
